slipdeck/__init__.py
slipdeck/cli.py
slipdeck/pdf_creator.py
slipdeck/pdf_processor.py
slipdeck/config/config_manager.py
slipdeck/models/order.py
slipdeck/models/pull_card.py
slipdeck/utilities/price_util.py
slipdeck-0.2.0.dist-info/METADATA
slipdeck-0.2.0.dist-info/WHEEL
slipdeck-0.2.0.dist-info/entry_points.txt
slipdeck-0.2.0.dist-info/licenses/LICENSE
slipdeck-0.2.0.dist-info/RECORD
