Metadata-Version: 2.4
Name: slipdeck
Version: 0.2.0
Summary: Quickly generate professional packing slips for TCGPlayer and other marketplaces.
Project-URL: Homepage, https://github.com/star3llc/slipdeck
Project-URL: Bug Tracker, https://github.com/star3llc/slipdeck/issues
Author: Star Three LLC
License-Expression: MIT
License-File: LICENSE
Classifier: License :: OSI Approved :: MIT License
Classifier: Operating System :: OS Independent
Classifier: Programming Language :: Python :: 3
Requires-Python: >=3.7
Requires-Dist: fpdf2==2.8.2
Requires-Dist: pdfplumber==0.11.5
Requires-Dist: pydantic==2.10.6
Requires-Dist: pypdf2==3.0.1
Requires-Dist: python-dotenv==1.0.1
Requires-Dist: rich==13.9.4
Requires-Dist: typer>=0.9.0
